examples/__init__.py
examples/test_default_config.py
pf_py_ymlenv/__init__.py
pf_py_ymlenv/pfpy_config_loader.py
pf_py_ymlenv/pfpy_config_obj.py
pf_py_ymlenv/pfpy_file_util.py
pf_py_ymlenv/yml_util.py
PF_PY_YMLEnv-1.0.1.dist-info/LICENSE
PF_PY_YMLEnv-1.0.1.dist-info/METADATA
PF_PY_YMLEnv-1.0.1.dist-info/WHEEL
PF_PY_YMLEnv-1.0.1.dist-info/top_level.txt
PF_PY_YMLEnv-1.0.1.dist-info/RECORD
